CONTRIBUTORS.txt
MANIFEST.in
README.txt
plonetheme.pyar-configure.zcml
setup.cfg
setup.py
docs/HISTORY.txt
docs/INSTALL.txt
docs/LICENSE.GPL
docs/LICENSE.txt
plonetheme/__init__.py
plonetheme.pyar.egg-info/PKG-INFO
plonetheme.pyar.egg-info/SOURCES.txt
plonetheme.pyar.egg-info/dependency_links.txt
plonetheme.pyar.egg-info/entry_points.txt
plonetheme.pyar.egg-info/namespace_packages.txt
plonetheme.pyar.egg-info/not-zip-safe
plonetheme.pyar.egg-info/paster_plugins.txt
plonetheme.pyar.egg-info/requires.txt
plonetheme.pyar.egg-info/top_level.txt
plonetheme/pyar/__init__.py
plonetheme/pyar/configure.zcml
plonetheme/pyar/profiles.zcml
plonetheme/pyar/setuphandlers.py
plonetheme/pyar/skins.zcml
plonetheme/pyar/tests.py
plonetheme/pyar/version.txt
plonetheme/pyar/browser/__init__.py
plonetheme/pyar/browser/configure.zcml
plonetheme/pyar/browser/interfaces.py
plonetheme/pyar/browser/viewlets.py
plonetheme/pyar/browser/images/README.txt
plonetheme/pyar/browser/images/arrow.gif
plonetheme/pyar/browser/images/button_background.gif
plonetheme/pyar/browser/images/hover_arrow.gif
plonetheme/pyar/browser/images/login_button.jpg
plonetheme/pyar/browser/images/print.png
plonetheme/pyar/browser/images/rss.png
plonetheme/pyar/browser/images/search_button.gif
plonetheme/pyar/browser/images/selected_arrow.gif
plonetheme/pyar/browser/images/selected_folder_arrow.gif
plonetheme/pyar/browser/images/send_to.png
plonetheme/pyar/browser/images/sky.gif
plonetheme/pyar/browser/images/solpiente.png
plonetheme/pyar/browser/images/top_background.jpg
plonetheme/pyar/browser/portlets/__init__.py
plonetheme/pyar/browser/portlets/login.pt
plonetheme/pyar/browser/portlets/login.py
plonetheme/pyar/browser/portlets/navigation.pt
plonetheme/pyar/browser/portlets/navigation.py
plonetheme/pyar/browser/portlets/navigation_recurse.pt
plonetheme/pyar/browser/portlets/news.pt
plonetheme/pyar/browser/portlets/news.py
plonetheme/pyar/browser/stylesheets/README.txt
plonetheme/pyar/browser/stylesheets/main.css
plonetheme/pyar/browser/stylesheets/navtree.css
plonetheme/pyar/browser/stylesheets/news.css
plonetheme/pyar/browser/stylesheets/portlets.css
plonetheme/pyar/browser/templates/path_bar.pt
plonetheme/pyar/browser/templates/personal_bar.pt
plonetheme/pyar/browser/templates/site_actions.pt
plonetheme/pyar/profiles/default/cssregistry.xml
