Metadata-Version: 1.0
Name: plonetheme.pyar
Version: 1.0dev-r110708
Summary: A PyAr theme for Plone 3.x
Home-page: http://svn.plone.org/svn/collective/plonetheme.pyar
Author: Javier Mansilla
Author-email: jmansilla@machinalis.com
License: GPL
Keywords: web zope plone theme python argentina
Platform: UNKNOWN
Classifier: Framework :: Plone
Classifier: Programming Language :: Python
Classifier: Topic :: Software Development :: Libraries :: Python Modules
